[
  {
    "line": 1,
    "elements": [
      {
        "start_timestamp": "2023-10-22T15:26:00.804Z",
        "before": [
          {
            "result": {
              "duration": 7586105400,
              "status": "passed"
            },
            "match": {
              "location": "CucumberJava.Cart.beforeScenario()"
            }
          },
          {
            "result": {
              "duration": 5966594000,
              "status": "passed"
            },
            "match": {
              "location": "CucumberJava.Login.beforeScenario()"
            }
          },
          {
            "result": {
              "duration": 2689456800,
              "status": "passed"
            },
            "match": {
              "location": "CucumberJava.Register.beforeScenario()"
            }
          }
        ],
        "line": 12,
        "name": "Logging",
        "description": "",
        "id": "beer-cans;logging;;2",
        "type": "scenario",
        "keyword": "Scenario Outline",
        "steps": [
          {
            "result": {
              "duration": 615306900,
              "status": "passed"
            },
            "line": 4,
            "name": "user navigate to the login page",
            "match": {
              "location": "CucumberJava.Login.userAreOnTheLoginPage()"
            },
            "keyword": "Given "
          },
          {
            "result": {
              "duration": 76977800,
              "status": "passed"
            },
            "line": 5,
            "name": "User enters valid email address \"wp900622@gmail.com\" into the email field",
            "match": {
              "arguments": [
                {
                  "val": "\"wp900622@gmail.com\"",
                  "offset": 32
                }
              ],
              "location": "CucumberJava.Login.userEntersAnd(java.lang.String)"
            },
            "keyword": "When "
          },
          {
            "result": {
              "duration": 60909200,
              "status": "passed"
            },
            "line": 6,
            "name": "User enters valid password \"12345\" into the password field",
            "match": {
              "arguments": [
                {
                  "val": "\"12345\"",
                  "offset": 27
                }
              ],
              "location": "CucumberJava.Login.userEntersValidPasswordIntoThePasswordField(java.lang.String)"
            },
            "keyword": "And "
          },
          {
            "result": {
              "duration": 329485800,
              "status": "passed"
            },
            "line": 7,
            "name": "User clicks on the login button",
            "match": {
              "location": "CucumberJava.Login.userClicksOnTheLoginButton()"
            },
            "keyword": "And "
          },
          {
            "result": {
              "duration": 1037538800,
              "status": "passed"
            },
            "line": 8,
            "name": "user should be logged in",
            "match": {
              "location": "CucumberJava.Login.userShouldBeLoggedIn()"
            },
            "keyword": "Then "
          }
        ]
      },
      {
        "start_timestamp": "2023-10-22T15:26:19.323Z",
        "before": [
          {
            "result": {
              "duration": 6230504700,
              "status": "passed"
            },
            "match": {
              "location": "CucumberJava.Cart.beforeScenario()"
            }
          },
          {
            "result": {
              "duration": 7914494900,
              "status": "passed"
            },
            "match": {
              "location": "CucumberJava.Login.beforeScenario()"
            }
          },
          {
            "result": {
              "duration": 6441146900,
              "status": "passed"
            },
            "match": {
              "location": "CucumberJava.Register.beforeScenario()"
            }
          }
        ],
        "line": 14,
        "name": "Logging in with invalid credentials",
        "description": "",
        "id": "beer-cans;logging-in-with-invalid-credentials",
        "type": "scenario",
        "keyword": "Scenario",
        "steps": [
          {
            "result": {
              "duration": 878058100,
              "status": "passed"
            },
            "line": 15,
            "name": "user navigate to the login page",
            "match": {
              "location": "CucumberJava.Login.userAreOnTheLoginPage()"
            },
            "keyword": "Given "
          },
          {
            "result": {
              "duration": 91069400,
              "status": "passed"
            },
            "line": 16,
            "name": "User enters valid email address \"wp900622@gmail.com\" into the email field",
            "match": {
              "arguments": [
                {
                  "val": "\"wp900622@gmail.com\"",
                  "offset": 32
                }
              ],
              "location": "CucumberJava.Login.userEntersAnd(java.lang.String)"
            },
            "keyword": "When "
          },
          {
            "result": {
              "duration": 56946800,
              "status": "passed"
            },
            "line": 17,
            "name": "User enters invalid password \" \" into the password field",
            "match": {
              "arguments": [
                {
                  "val": "\" \"",
                  "offset": 29
                }
              ],
              "location": "CucumberJava.Login.userEntersInvalidPasswordIntoThePasswordField(java.lang.String)"
            },
            "keyword": "And "
          },
          {
            "result": {
              "duration": 234161700,
              "status": "passed"
            },
            "line": 18,
            "name": "User clicks on the login button",
            "match": {
              "location": "CucumberJava.Login.userClicksOnTheLoginButton()"
            },
            "keyword": "And "
          },
          {
            "result": {
              "duration": 833123000,
              "status": "passed"
            },
            "line": 19,
            "name": "user should get an error message about invalid credentials",
            "match": {
              "location": "CucumberJava.Login.userShouldGetAnErrorMessageAboutInvalidCredentials()"
            },
            "keyword": "Then "
          }
        ]
      }
    ],
    "name": "Beer cans",
    "description": "",
    "id": "beer-cans",
    "keyword": "Feature",
    "uri": "classpath:features/Login.feature",
    "tags": []
  },
  {
    "line": 1,
    "elements": [
      {
        "start_timestamp": "2023-10-22T15:26:42.017Z",
        "before": [
          {
            "result": {
              "duration": 5793270200,
              "status": "passed"
            },
            "match": {
              "location": "CucumberJava.Cart.beforeScenario()"
            }
          },
          {
            "result": {
              "duration": 6172476800,
              "status": "passed"
            },
            "match": {
              "location": "CucumberJava.Login.beforeScenario()"
            }
          },
          {
            "result": {
              "duration": 3025595400,
              "status": "passed"
            },
            "match": {
              "location": "CucumberJava.Register.beforeScenario()"
            }
          }
        ],
        "line": 15,
        "name": "User registers with valid data",
        "description": "",
        "id": "registering-a-new-user;user-registers-with-valid-data;;2",
        "type": "scenario",
        "keyword": "Scenario Outline",
        "steps": [
          {
            "result": {
              "duration": 296866200,
              "status": "passed"
            },
            "line": 3,
            "name": "user navigate to the register page",
            "match": {
              "location": "CucumberJava.Register.userNavigateToTheRegisterPage()"
            },
            "keyword": "Given "
          },
          {
            "result": {
              "duration": 60716400,
              "status": "passed"
            },
            "line": 4,
            "name": "user enters \"John\" into the first name field",
            "match": {
              "arguments": [
                {
                  "val": "\"John\"",
                  "offset": 12
                }
              ],
              "location": "CucumberJava.Register.userEntersIntoTheFirstNameField(java.lang.String)"
            },
            "keyword": "When "
          },
          {
            "result": {
              "duration": 53068400,
              "status": "passed"
            },
            "line": 5,
            "name": "user enters \"Doe\" into the last name field",
            "match": {
              "arguments": [
                {
                  "val": "\"Doe\"",
                  "offset": 12
                }
              ],
              "location": "CucumberJava.Register.userEntersIntoTheLastNameField(java.lang.String)"
            },
            "keyword": "And "
          },
          {
            "result": {
              "duration": 78148600,
              "status": "passed"
            },
            "line": 6,
            "name": "user enters \"johndoe@gmail.com\" into the email field",
            "match": {
              "arguments": [
                {
                  "val": "\"johndoe@gmail.com\"",
                  "offset": 12
                }
              ],
              "location": "CucumberJava.Register.userEntersIntoTheEmailField(java.lang.String)"
            },
            "keyword": "And "
          },
          {
            "result": {
              "duration": 73851300,
              "status": "passed"
            },
            "line": 7,
            "name": "user enters \"123456789\" into the telephone field",
            "match": {
              "arguments": [
                {
                  "val": "\"123456789\"",
                  "offset": 12
                }
              ],
              "location": "CucumberJava.Register.userEntersIntoTheTelephoneField(java.lang.String)"
            },
            "keyword": "And "
          },
          {
            "result": {
              "duration": 75240200,
              "status": "passed"
            },
            "line": 8,
            "name": "user enters \"123456\"  into the password field",
            "match": {
              "arguments": [
                {
                  "val": "\"123456\"",
                  "offset": 12
                }
              ],
              "location": "CucumberJava.Register.userEntersIntoThePasswordField(java.lang.String)"
            },
            "keyword": "And "
          },
          {
            "result": {
              "duration": 62060800,
              "status": "passed"
            },
            "line": 9,
            "name": "user enters \"123456\" into the password confirm field",
            "match": {
              "arguments": [
                {
                  "val": "\"123456\"",
                  "offset": 12
                }
              ],
              "location": "CucumberJava.Register.userEntersIntoThePasswordConfirmField(java.lang.String)"
            },
            "keyword": "And "
          },
          {
            "result": {
              "duration": 47338500,
              "status": "passed"
            },
            "line": 10,
            "name": "user clicks on the privacy policy checkbox",
            "match": {
              "location": "CucumberJava.Register.userClicksOnThePrivacyPolicyCheckbox()"
            },
            "keyword": "And "
          },
          {
            "result": {
              "duration": 250883200,
              "status": "passed"
            },
            "line": 11,
            "name": "user clicks on the continue button",
            "match": {
              "location": "CucumberJava.Register.userClicksOnTheContinueButton()"
            },
            "keyword": "And "
          },
          {
            "result": {
              "duration": 27725000,
              "status": "passed"
            },
            "line": 12,
            "name": "user should be registered successfully",
            "match": {
              "location": "CucumberJava.Register.userShouldBeRegisteredSuccessfully()"
            },
            "keyword": "Then "
          }
        ]
      }
    ],
    "name": "Registering a new user",
    "description": "",
    "id": "registering-a-new-user",
    "keyword": "Feature",
    "uri": "classpath:features/Register.feature",
    "tags": []
  },
  {
    "line": 1,
    "elements": [
      {
        "start_timestamp": "2023-10-22T15:26:58.049Z",
        "before": [
          {
            "result": {
              "duration": 9717297200,
              "status": "passed"
            },
            "match": {
              "location": "CucumberJava.Cart.beforeScenario()"
            }
          },
          {
            "result": {
              "duration": 6980418300,
              "status": "passed"
            },
            "match": {
              "location": "CucumberJava.Login.beforeScenario()"
            }
          },
          {
            "result": {
              "duration": 6498844500,
              "status": "passed"
            },
            "match": {
              "location": "CucumberJava.Register.beforeScenario()"
            }
          }
        ],
        "line": 2,
        "name": "Add new item to the cart",
        "description": "",
        "id": "add-new-item-to-the-cart;add-new-item-to-the-cart",
        "type": "scenario",
        "keyword": "Scenario",
        "steps": [
          {
            "result": {
              "duration": 505470300,
              "status": "passed"
            },
            "line": 3,
            "name": "User navigate to the Phones\u0026PDAs page",
            "match": {
              "location": "CucumberJava.Cart.userNavigateToThePhonesPDAsPage()"
            },
            "keyword": "Given "
          },
          {
            "result": {
              "duration": 704214000,
              "status": "passed"
            },
            "line": 4,
            "name": "I click on the iPhone link",
            "match": {
              "location": "CucumberJava.Cart.iClickOnTheIPhoneLink()"
            },
            "keyword": "When "
          },
          {
            "result": {
              "duration": 95594600,
              "status": "passed"
            },
            "line": 5,
            "name": "I enter 1 in the quantity field",
            "match": {
              "arguments": [
                {
                  "val": "1",
                  "offset": 8
                }
              ],
              "location": "CucumberJava.Cart.iEnterInTheQuantityField(int)"
            },
            "keyword": "And "
          },
          {
            "result": {
              "duration": 51998000,
              "status": "passed"
            },
            "line": 6,
            "name": "I click on the Add to cart button",
            "match": {
              "location": "CucumberJava.Cart.iClickOnTheAddToCartButton()"
            },
            "keyword": "And "
          },
          {
            "result": {
              "duration": 144323400,
              "status": "passed"
            },
            "line": 7,
            "name": "I should see the Item added to cart message",
            "match": {
              "location": "CucumberJava.Cart.iShouldSeeTheItemAddedToCartMessage()"
            },
            "keyword": "Then "
          },
          {
            "result": {
              "duration": 53744300,
              "status": "passed"
            },
            "line": 8,
            "name": "I click cart button",
            "match": {
              "location": "CucumberJava.Cart.iClickCartButton()"
            },
            "keyword": "And "
          },
          {
            "result": {
              "duration": 16190700,
              "status": "passed"
            },
            "line": 9,
            "name": "I should see the item in the cart",
            "match": {
              "location": "CucumberJava.Cart.iShouldSeeTheItemInTheCart()"
            },
            "keyword": "Then "
          }
        ]
      }
    ],
    "name": "Add new item to the cart",
    "description": "",
    "id": "add-new-item-to-the-cart",
    "keyword": "Feature",
    "uri": "classpath:features/Shopping.feature",
    "tags": []
  }
]